paddleONNXOCR/__init__.py
paddleONNXOCR/image_loader.py
paddleONNXOCR/image_rotate.py
paddleONNXOCR/models_enum.py
paddleONNXOCR/utils.py
paddleONNXOCR/predict/__init__.py
paddleONNXOCR/predict/ocr_dataclass.py
paddleONNXOCR/predict/predict_base.py
paddleONNXOCR/predict/predict_cls.py
paddleONNXOCR/predict/predict_det.py
paddleONNXOCR/predict/predict_doc_cls.py
paddleONNXOCR/predict/predict_layout.py
paddleONNXOCR/predict/predict_rec.py
paddleONNXOCR/predict/predict_system.py
paddleONNXOCR/predict/predict_table_cell.py
paddleONNXOCR/predict/predict_table_cls.py
paddleONNXOCR/predict/predict_uvdoc.py
paddleONNXOCR/static/ppocrv5_dict.txt
paddle_onnxocr-0.0.7.dist-info/licenses/LICENSE
paddle_onnxocr-0.0.7.dist-info/METADATA
paddle_onnxocr-0.0.7.dist-info/WHEEL
paddle_onnxocr-0.0.7.dist-info/top_level.txt
paddle_onnxocr-0.0.7.dist-info/RECORD
