Metadata-Version: 2.4
Name: paddle_onnxocr
Version: 0.0.7
Summary: paddleOCR的onnx实现
Author-email: wyy-holding <944581678@qq.com>
License-Expression: MIT
Project-URL: Homepage, https://github.com/wyy-holding/paddleONNXOCR
Project-URL: Issues, https://github.com/wyy-holding/paddleONNXOCR/issues
Classifier: Programming Language :: Python :: 3
Classifier: Operating System :: OS Independent
Requires-Python: >=3.10
License-File: LICENSE
Requires-Dist: opencv-python-headless
Requires-Dist: shapely
Requires-Dist: pyclipper
Requires-Dist: onnxruntime
Requires-Dist: pillow
Requires-Dist: validators
Requires-Dist: aiohttp
Requires-Dist: psutil
Requires-Dist: deskew
Requires-Dist: modelscope
Dynamic: license-file
